Workbook

Sheet README
A1: Capex Cloud — Hyperscaler Capex Consensus, Street High & PP&E Breakdown
A3: Built 2026-06-11. BBG data pulled 2026-06-11 11:38 via Capstone wrapper (http://10.10.60.104/api/). All $ in millions unless noted.
A5: TABS:
A6: Fwd Windows — BEst capex, next-12m (1BF) and months 12-24 (2BF) blended-forward windows + cumulative 24m.
A7: CY vs Capstone — calendar-year capex: Street consensus vs street high vs Capstone house estimates. MSFT (FY Jun) and ORCL (FY May) calendarized from calendar quarters (reported actuals + BEst kFQ quarterly consensus).
A8: Fiscal Years — FY1-FY3 consensus per company with street high/low, # estimates, YoY and capex intensity.
A9: Yearly History — calendar-year capex 2015-2025 actual + 2026-27E consensus; revenue and capex/revenue intensity.
A10: Revisions — weekly BEst capex history (rolling 1BF/2BF windows) since Jan-2023, per company + Big-5 total.
A11: PPE <ticker> — gross property & equipment by category from official filings, with Equipment vs long-term-asset split.
A12: PPE Summary — cross-company Equipment vs LT comparison, latest fiscal year.
A14: COLOR CODE: blue = hardcoded source data · black = formulas · green = cross-sheet links · yellow fill = Capstone house assumptions.
A16: PP&E SOURCES:
... A24: Consensus notes: BEST_CAPEX mean / |BEST_CAPEX_LO| = street-HIGH spend / |BEST_CAPEX_HI| = street-LOW (BBG capex is negative). Broker attribution is not exposed by the wrapper (Terminal EE/ANR).

Sheet Fwd Windows
A1: Forward windows — BEst capex consensus & street range (US$ mn)
A2: Blended-forward windows roll from 2026-06-11. 1BF = next 12 months, 2BF = months 12-24. Source: Bloomberg bdp BEST_CAPEX / BEST_CAPEX_LO / BEST_CAPEX_HI / BEST_CAPEX_NUMEST / BEST_SALES, BEST_FPERIOD_OVERRIDE=1BF/2BF, pulled 2026-06-11 11:38.
A4: Company | B4: NTM mean | C4: NTM street high | D4: NTM street low | E4: NTM # est | F4: NTM BEst revenue | G4: NTM capex/rev | H4: 12-24M mean | I4: 12-24M street high | J4: 12-24M street low | K4: 12-24M # est | L4: Cum 24M mean | M4: Cum 24M street high
A5: Microsoft | B5: 177406 | C5: 235592 | D5: 75232 | E5: 37 | F5: 381188 | G5: =IF(F5=0,"-",B5/F5) -> 0.4654029 | H5: 200884 | I5: 274200 | J5: 124648 | K5: 28 | L5: =B5+H5 -> 378290 | M5: =C5+I5 -> 509792
A6: Amazon | B6: 212156 | C6: 238691 | D6: 162834 | E6: 30 | F6: 873204 | G6: =IF(F6=0,"-",B6/F6) -> 0.2429627 | H6: 231403 | I6: 312885 | J6: 159027 | K6: 25 | L6: =B6+H6 -> 443559 | M6: =C6+I6 -> 551576
A7: Alphabet | B7: 211122 | C7: 242370 | D7: 157857 | E7: 47 | F7: 459243 | G7: =IF(F7=0,"-",B7/F7) -> 0.4597174 | H7: 248385 | I7: 324835 | J7: 131344 | K7: 40 | L7: =B7+H7 -> 459507 | M7: =C7+I7 -> 567205
A8: Meta | B8: 146769 | C8: 170497 | D8: 114247 | E8: 42 | F8: 274626 | G8: =IF(F8=0,"-",B8/F8) -> 0.53443228 | H8: 168878 | I8: 230242 | J8: 112378 | K8: 37 | L8: =B8+H8 -> 315647 | M8: =C8+I8 -> 400739
A9: Oracle | B9: 80465 | C9: 130682 | D9: 22756 | E9: 33 | F9: 90320 | G9: =IF(F9=0,"-",B9/F9) -> 0.89088795 | H9: 96629 | I9: 150047 | J9: 40942 | K9: 30 | L9: =B9+H9 -> 177094 | M9: =C9+I9 -> 280729
A10: Big-5 total | B10: =SUM(B5:B9) -> 827918 | C10: =SUM(C5:C9) -> 1017832 | D10: =SUM(D5:D9) -> 532926 | F10: =SUM(F5:F9) -> 2078581 | H10: =SUM(H5:H9) -> 946179 | I10: =SUM(I5:I9) -> 1292209 | J10: =SUM(J5:J9) -> 568339 | L10: =SUM(L5:L9) -> 1774097 | M10: =SUM(M5:M9) -> 2310041
A12: Cumulative 24M street high sums per-window highs — indicative only (analyst sets differ per window).

Sheet CY vs Capstone
A1: Calendar-year capex — Street consensus vs street high vs Capstone (US$ mn)
A2: MSFT/ORCL calendarized: reported calendar quarters (actuals) + BEst quarterly consensus (kFQ) for unreported quarters; their street high sums most-aggressive quarterly estimates (composite). Dec-FY names map 1:1 to FY fields. Capstone = house estimates (Felipe, Jun-2026). CY2025 = reported actuals.
A4: Company | B4: CY2025 consensus | C4: CY2025 street high | D4: CY2025 Capstone | E4: CY2025 Δ Capstone | F4: CY2026E consensus | G4: CY2026E street high | H4: CY2026E Capstone | I4: CY2026E Δ Capstone | J4: CY2027E consensus | K4: CY2027E street high | L4: CY2027E Capstone | M4: CY2027E Δ Capstone
A5: Microsoft | B5: 83094 | D5: 104647 | E5: =IF(B5=0,"-",D5/B5-1) -> 0.25938094 | F5: 157860 | G5: 193464 | H5: 170000 | I5: =IF(F5=0,"-",H5/F5-1) -> 0.076903585 | J5: 192476 | K5: 252257 | L5: 280000 | M5: =IF(J5=0,"-",L5/J5-1) -> 0.45472682
A6: Amazon | B6: 131819 | D6: 132000 | E6: =IF(B6=0,"-",D6/B6-1) -> 0.0013730949 | F6: 199113 | G6: 208094 | H6: 200000 | I6: =IF(F6=0,"-",H6/F6-1) -> 0.0044547568 | J6: 228460 | K6: 276937 | L6: 300000 | M6: =IF(J6=0,"-",L6/J6-1) -> 0.31314016
A7: Alphabet | B7: 91447 | D7: 91400 | E7: =IF(B7=0,"-",D7/B7-1) -> -0.00051395891 | F7: 186523 | G7: 192174 | H7: 180000 | I7: =IF(F7=0,"-",H7/F7-1) -> -0.034971558 | J7: 241872 | K7: 305114 | L7: 285000 | M7: =IF(J7=0,"-",L7/J7-1) -> 0.17830919
A8: Meta | B8: 69691 | D8: 72000 | E8: =IF(B8=0,"-",D8/B8-1) -> 0.033131968 | F8: 134816 | G8: 145179 | H8: 125000 | I8: =IF(F8=0,"-",H8/F8-1) -> -0.072810349 | J8: 161709 | K8: 202144 | L8: 160000 | M8: =IF(J8=0,"-",L8/J8-1) -> -0.010568367
A9: Oracle | B9: 35477 | D9: 33102 | E9: =IF(B9=0,"-",D9/B9-1) -> -0.066944781 | F9: 71090 | G9: 85128 | H9: 92000 | I9: =IF(F9=0,"-",H9/F9-1) -> 0.2941342 | J9: 89907 | K9: 150593 | L9: 150000 | M9: =IF(J9=0,"-",L9/J9-1) -> 0.66839067
A10: Big-5 total | B10: =SUM(B5:B9) -> 411528 | C10: =SUM(C5:C9) -> 0 | D10: =SUM(D5:D9) -> 433149 | E10: =IF(B10=0,"-",D10/B10-1) -> 0.052538345 | F10: =SUM(F5:F9) -> 749402 | G10: =SUM(G5:G9) -> 824039 | H10: =SUM(H5:H9) -> 767000 | I10: =IF(F10=0,"-",H10/F10-1) -> 0.023482724 | J10: =SUM(J5:J9) -> 914424 | K10: =SUM(K5:K9) -> 1187045 | L10: =SUM(L5:L9) -> 1175000 | M10: =IF(J10=0,"-",L10/J10-1) -> 0.2849619
A12: MSFT CY2025 Capstone ($104.6bn) vs reported cash capex ($83.1bn): definition difference (e.g. finance leases).

Sheet Fiscal Years
A1: Fiscal years FY1-FY3 — BEst capex consensus (US$ mn)
A2: FY labels are company-specific (MSFT FY ends Jun, ORCL May, others Dec). ORCL FY26 just reported -> its FY1 = FY27. Prior actual = last reported fiscal year (used for FY1 YoY).
A4: Company | B4: Period (FY end) | C4: Consensus mean | D4: Street high | E4: Street low | F4: # est | G4: Prior actual / mean | H4: YoY (mean) | I4: Capex / BEst rev
A5: Microsoft | B5: FY26 (Jun-26) | C5: 116904 | D5: 151494 | E5: 71561 | F5: 37 | G5: 64551 | H5: =IF(G5=0,"-",C5/G5-1) -> 0.81103314 | I5: =C5/329468 -> 0.35482657
B6: FY27 (Jun-27) | C6: 180578 | D6: 240000 | E6: 75424 | F6: 37 | G6: =C5 -> 116904 | H6: =IF(G6=0,"-",C6/G6-1) -> 0.54466913 | I6: =C6/384028 -> 0.47022092
B7: FY28 (Jun-28) | C7: 201953 | D7: 276000 | E7: 127239 | F7: 28 | G7: =C6 -> 180578 | H7: =IF(G7=0,"-",C7/G7-1) -> 0.1183699 | I7: =C7/452637 -> 0.44616989
A8: Amazon | B8: FY26 (Dec-26) | C8: 199113 | D8: 208094 | E8: 163470 | F8: 30 | G8: 131819 | H8: =IF(G8=0,"-",C8/G8-1) -> 0.51050304 | I8: =C8/824999 -> 0.24134938
B9: FY27 (Dec-27) | C9: 228460 | D9: 276937 | E9: 162039 | F9: 30 | G9: =C8 -> 199113 | H9: =IF(G9=0,"-",C9/G9-1) -> 0.14738867 | I9: =C9/933608 -> 0.24470656
B10: FY28 (Dec-28) | C10: 235113 | D10: 358211 | E10: 155229 | F10: 19 | G10: =C9 -> 228460 | H10: =IF(G10=0,"-",C10/G10-1) -> 0.029121072 | I10: =C10/1035309 -> 0.22709452
A11: Alphabet | B11: FY26 (Dec-26) | C11: 186523 | D11: 192174 | E11: 179674 | F11: 48 | G11: 91447 | H11: =IF(G11=0,"-",C11/G11-1) -> 1.0396842 | I11: =C11/420342 -> 0.44374105
B12: FY27 (Dec-27) | C12: 241872 | D12: 305114 | E12: 130586 | F12: 47 | G12: =C11 -> 186523 | H12: =IF(G12=0,"-",C12/G12-1) -> 0.29674088 | I12: =C12/507990 -> 0.47613536
B13: FY28 (Dec-28) | C13: 256598 | D13: 349700 | E13: 132300 | F13: 32 | G13: =C12 -> 241872 | H13: =IF(G13=0,"-",C13/G13-1) -> 0.060883442 | I13: =C13/603211 -> 0.4253868
A14: Meta | B14: FY26 (Dec-26) | C14: 134816 | D14: 145179 | E14: 114620 | F14: 43 | G14: 69691 | H14: =IF(G14=0,"-",C14/G14-1) -> 0.93448221 | I14: =C14/253029 -> 0.53280849
B15: FY27 (Dec-27) | C15: 161709 | D15: 202144 | E15: 113780 | F15: 42 | G15: =C14 -> 134816 | H15: =IF(G15=0,"-",C15/G15-1) -> 0.19947929 | I15: =C15/301689 -> 0.53601225
B16: FY28 (Dec-28) | C16: 177916 | D16: 265670 | E16: 110611 | F16: 31 | G16: =C15 -> 161709 | H16: =IF(G16=0,"-",C16/G16-1) -> 0.10022324 | I16: =C16/353460 -> 0.5033554
A17: Oracle | B17: FY27 (May-27) | C17: 79883 | D17: 130000 | E17: 22121 | F17: 34 | G17: 55663 | H17: =IF(G17=0,"-",C17/G17-1) -> 0.43511848 | I17: =C17/89071 -> 0.89684634
B18: FY28 (May-28) | C18: 96753 | D18: 149772 | E18: 40542 | F18: 31 | G18: =C17 -> 79883 | H18: =IF(G18=0,"-",C18/G18-1) -> 0.21118386 | I18: =C18/130895 -> 0.73916498
B19: FY29 (May-29) | C19: 92156 | D19: 160000 | E19: 55410 | F19: 19 | G19: =C18 -> 96753 | H19: =IF(G19=0,"-",C19/G19-1) -> -0.047512739 | I19: =C19/182424 -> 0.50517476
A21: Capex / BEst rev divides consensus capex by BEst revenue of the same fiscal period (revenue hardcoded in formula; source BEST_SALES).

Sheet Yearly History
A1: Calendar-year capex & intensity — actuals 2015-25, consensus 2026-27E (US$ mn)
A2: Actuals = sum of the 4 calendar quarters (bdh CAPITAL_EXPEND / SALES_REV_TURN; fiscal-quarter ends mapped to calendar years; MSFT and ORCL therefore calendarized). 2026E/27E = CY consensus from 'CY vs Capstone' logic.
A4: CAPEX | B4: 2015 | C4: 2016 | D4: 2017 | E4: 2018 | F4: 2019 | G4: 2020 | H4: 2021 | I4: 2022 | J4: 2023 | K4: 2024 | L4: 2025 | M4: 2026E | N4: 2027E
A5: Microsoft | B5: 6552 | C5: 9114 | D5: 8696 | E5: 14223 | F5: 13546 | G5: 17592 | H5: 23216 | I5: 24768 | J5: 35202 | K5: 55552 | L5: 83094 | M5: 157860 | N5: 192476
A6: Amazon | B6: 4588 | C6: 7804 | D6: 11955 | E6: 13426 | F6: 16861 | G6: 40141 | H6: 61053 | I6: 63645 | J6: 52729 | K6: 82999 | L6: 131819 | M6: 199113 | N6: 228460
A7: Alphabet | B7: 9927 | C7: 10212 | D7: 13184 | E7: 25139 | F7: 23548 | G7: 22281 | H7: 24640 | I7: 31485 | J7: 32251 | K7: 52535 | L7: 91447 | M7: 186523 | N7: 241872
A8: Meta | B8: 2523 | C8: 4491 | D8: 6732 | E8: 13980 | F8: 15102 | G8: 15115 | H8: 18628 | I8: 31431 | J8: 27266 | K8: 37256 | L8: 69691 | M8: 134816 | N8: 161709
A9: Oracle | B9: 1606 | C9: 1604 | D9: 2037 | E9: 1468 | F9: 1591 | G9: 1833 | H9: 4122 | I9: 6678 | J9: 6935 | K9: 10745 | L9: 35477 | M9: 71090 | N9: 89907
A10: Big-5 total | B10: =SUM(B5:B9) -> 25196 | C10: =SUM(C5:C9) -> 33225 | D10: =SUM(D5:D9) -> 42604 | E10: =SUM(E5:E9) -> 68236 | F10: =SUM(F5:F9) -> 70648 | G10: =SUM(G5:G9) -> 96962 | H10: =SUM(H5:H9) -> 131659 | I10: =SUM(I5:I9) -> 158007 | ... N10: =SUM(N5:N9) -> 914424
A12: REVENUE | B12: 2015 | C12: 2016 | D12: 2017 | E12: 2018 | F12: 2019 | G12: 2020 | H12: 2021 | I12: 2022 | J12: 2023 | K12: 2024 | L12: 2025
A13: Microsoft | B13: 90072 | C13: 92745 | D13: 102273 | E13: 118459 | F13: 134249 | G13: 153284 | H13: 184903 | I13: 204094 | J13: 227583 | K13: 261802 | L13: 305453
A14: Amazon | B14: 107007 | C14: 135987 | D14: 177866 | E14: 232887 | F14: 280522 | G14: 386064 | H14: 469822 | I14: 513983 | J14: 574785 | K14: 637959 | L14: 716924
A15: Alphabet | B15: 74989 | C15: 90272 | D15: 110855 | E15: 136819 | F15: 161857 | G15: 182527 | H15: 257637 | I15: 282836 | J15: 307394 | K15: 350018 | L15: 402836
A16: Meta | B16: 17927 | C16: 27638 | D16: 40653 | E16: 55838 | F16: 70697 | G16: 85966 | H16: 117929 | I16: 116609 | J16: 134901 | K16: 164500 | L16: 200965
A17: Oracle | B17: 37474 | C17: 37236 | D17: 38790 | E17: 39445 | F17: 39582 | G17: 39403 | H17: 41400 | I17: 46073 | J17: 51629 | K17: 54933 | L17: 61017
A19: CAPEX / REVENUE | B19: 2015 | C19: 2016 | D19: 2017 | E19: 2018 | F19: 2019 | G19: 2020 | H19: 2021 | I19: 2022 | J19: 2023 | K19: 2024 | L19: 2025
A20: Microsoft | B20: =IF(OR(B13="",B13=0),"-",B5/B13) -> 0.072741807 | C20: =IF(OR(C13="",C13=0),"-",C5/C13) -> 0.098269448 | D20: =IF(OR(D13="",D13=0),"-",D5/D13) -> 0.085027329 | E20: =IF(OR(E13="",E13=0),"-",E5/E13) -> 0.12006686 | F20: =IF(OR(F13="",F13=0),"-",F5/F13) -> 0.10090206 | G20: =IF(OR(G13="",G13=0),"-",G5/G13) -> 0.11476736 | H20: =IF(OR(H13="",H13=0),"-",H5/H13) -> 0.12555772 | I20: =IF(OR(I13="",I13=0),"-",I5/I13) -> 0.12135585 | ... L20: =IF(OR(L13="",L13=0),"-",L5/L13) -> 0.2720353
A21: Amazon | B21: =IF(OR(B14="",B14=0),"-",B6/B14) -> 0.0428757 | C21: =IF(OR(C14="",C14=0),"-",C6/C14) -> 0.057387839 | D21: =IF(OR(D14="",D14=0),"-",D6/D14) -> 0.06721352 | E21: =IF(OR(E14="",E14=0),"-",E6/E14) -> 0.057650277 | F21: =IF(OR(F14="",F14=0),"-",F6/F14) -> 0.060105803 | G21: =IF(OR(G14="",G14=0),"-",G6/G14) -> 0.10397499 | H21: =IF(OR(H14="",H14=0),"-",H6/H14) -> 0.12994921 | I21: =IF(OR(I14="",I14=0),"-",I6/I14) -> 0.12382705 | ... L21: =IF(OR(L14="",L14=0),"-",L6/L14) -> 0.18386747
A22: Alphabet | B22: =IF(OR(B15="",B15=0),"-",B7/B15) -> 0.13237942 | C22: =IF(OR(C15="",C15=0),"-",C7/C15) -> 0.11312478 | D22: =IF(OR(D15="",D15=0),"-",D7/D15) -> 0.11893013 | E22: =IF(OR(E15="",E15=0),"-",E7/E15) -> 0.1837391 | F22: =IF(OR(F15="",F15=0),"-",F7/F15) -> 0.14548645 | G22: =IF(OR(G15="",G15=0),"-",G7/G15) -> 0.12206961 | H22: =IF(OR(H15="",H15=0),"-",H7/H15) -> 0.095638437 | I22: =IF(OR(I15="",I15=0),"-",I7/I15) -> 0.11131893 | ... L22: =IF(OR(L15="",L15=0),"-",L7/L15) -> 0.22700801
A23: Meta | B23: =IF(OR(B16="",B16=0),"-",B8/B16) -> 0.14073744 | C23: =IF(OR(C16="",C16=0),"-",C8/C16) -> 0.16249367 | D23: =IF(OR(D16="",D16=0),"-",D8/D16) -> 0.16559663 | E23: =IF(OR(E16="",E16=0),"-",E8/E16) -> 0.25036713 | F23: =IF(OR(F16="",F16=0),"-",F8/F16) -> 0.21361585 | G23: =IF(OR(G16="",G16=0),"-",G8/G16) -> 0.17582533 | H23: =IF(OR(H16="",H16=0),"-",H8/H16) -> 0.15795945 | I23: =IF(OR(I16="",I16=0),"-",I8/I16) -> 0.2695418 | ... L23: =IF(OR(L16="",L16=0),"-",L8/L16) -> 0.34678178
A24: Oracle | B24: =IF(OR(B17="",B17=0),"-",B9/B17) -> 0.04285638 | C24: =IF(OR(C17="",C17=0),"-",C9/C17) -> 0.043076593 | D24: =IF(OR(D17="",D17=0),"-",D9/D17) -> 0.052513534 | E24: =IF(OR(E17="",E17=0),"-",E9/E17) -> 0.037216377 | F24: =IF(OR(F17="",F17=0),"-",F9/F17) -> 0.040195038 | G24: =IF(OR(G17="",G17=0),"-",G9/G17) -> 0.046519301 | H24: =IF(OR(H17="",H17=0),"-",H9/H17) -> 0.099565217 | I24: =IF(OR(I17="",I17=0),"-",I9/I17) -> 0.14494389 | ... L24: =IF(OR(L17="",L17=0),"-",L9/L17) -> 0.58142813
A26: CAPEX / REVENUE — CONSENSUS FWD | B26: FY1 period | C26: FY1 | D26: FY2 period | E26: FY2 | F26: FY3 period | G26: FY3
A27: Microsoft | B27: FY26 (Jun-26) | C27: ='Fiscal Years'!I5 -> 0.35482657 | D27: FY27 (Jun-27) | E27: ='Fiscal Years'!I6 -> 0.47022092 | F27: FY28 (Jun-28) | G27: ='Fiscal Years'!I7 -> 0.44616989
A28: Amazon | B28: FY26 (Dec-26) | C28: ='Fiscal Years'!I8 -> 0.24134938 | D28: FY27 (Dec-27) | E28: ='Fiscal Years'!I9 -> 0.24470656 | F28: FY28 (Dec-28) | G28: ='Fiscal Years'!I10 -> 0.22709452
A29: Alphabet | B29: FY26 (Dec-26) | C29: ='Fiscal Years'!I11 -> 0.44374105 | D29: FY27 (Dec-27) | E29: ='Fiscal Years'!I12 -> 0.47613536 | F29: FY28 (Dec-28) | G29: ='Fiscal Years'!I13 -> 0.4253868
A30: Meta | B30: FY26 (Dec-26) | C30: ='Fiscal Years'!I14 -> 0.53280849 | D30: FY27 (Dec-27) | E30: ='Fiscal Years'!I15 -> 0.53601225 | F30: FY28 (Dec-28) | G30: ='Fiscal Years'!I16 -> 0.5033554
A31: Oracle | B31: FY27 (May-27) | C31: ='Fiscal Years'!I17 -> 0.89684634 | D31: FY28 (May-28) | E31: ='Fiscal Years'!I18 -> 0.73916498 | F31: FY29 (May-29) | G31: ='Fiscal Years'!I19 -> 0.50517476
A33: Consensus-forward intensity = BEst capex / BEst revenue per fiscal year (links to Fiscal Years tab). Fiscal years mapped to their end-year; MSFT FY ends Jun and ORCL May, so these are indicative for the calendar grid above. Matches the dashed forward segments on the dashboard's History & Forecast tab.

Sheet Revisions
A1: Weekly BEst capex consensus — rolling forward windows (US$ mn)
A2: bdh BEST_CAPEX daily, downsampled W-FRI. Windows roll with the calendar; steps at earnings dates are true revisions. Source: Bloomberg, pulled 2026-06-11 11:38.
A4: Date | B4: MSFT 1BF | C4: AMZN 1BF | D4: GOOGL 1BF | E4: META 1BF | F4: ORCL 1BF | G4: Total 1BF | I4: MSFT 2BF | J4: AMZN 2BF | K4: GOOGL 2BF | L4: META 2BF | M4: ORCL 2BF | N4: Total 2BF
A5: 2023-01-06 | B5: 28043 | C5: 59509 | D5: 32997 | E5: 34170 | F5: 7971 | G5: =SUM(B5:F5) -> 162690 | I5: 30620 | J5: 63015 | K5: 35028 | L5: 33652 | M5: 7212 | N5: =SUM(I5:M5) -> 169527
A6: 2023-01-13 | B6: 28064 | C6: 59547 | D6: 32887 | E6: 34077 | F6: 7878 | G6: =SUM(B6:F6) -> 162453 | I6: 30617 | J6: 62955 | K6: 34852 | L6: 33611 | M6: 7154 | N6: =SUM(I6:M6) -> 169189
A7: 2023-01-20 | B7: 28116 | C7: 59540 | D7: 32999 | E7: 33983 | F7: 7833 | G7: =SUM(B7:F7) -> 162471 | I7: 30526 | J7: 62517 | K7: 34837 | L7: 33550 | M7: 7150 | N7: =SUM(I7:M7) -> 168580
A8: 2023-01-27 | B8: 27883 | C8: 59464 | D8: 32876 | E8: 33924 | F8: 7803 | G8: =SUM(B8:F8) -> 161950 | I8: 30584 | J8: 62309 | K8: 34861 | L8: 33500 | M8: 7146 | N8: =SUM(I8:M8) -> 168400
A9: 2023-02-03 | B9: 27933 | C9: 60869 | D9: 31729 | E9: 31745 | F9: 7773 | G9: =SUM(B9:F9) -> 160049 | I9: 30646 | J9: 64091 | K9: 33859 | L9: 31845 | M9: 7142 | N9: =SUM(I9:M9) -> 167583
A10: 2023-02-10 | B10: 27956 | C10: 60876 | D10: 31516 | E10: 31437 | F10: 7744 | G10: =SUM(B10:F10) -> 159529 | I10: 30540 | J10: 63691 | K10: 33626 | L10: 31741 | M10: 7138 | N10: =SUM(I10:M10) -> 166736
A11: 2023-02-17 | B11: 27919 | C11: 60457 | D11: 31487 | E11: 31386 | F11: 7714 | G11: =SUM(B11:F11) -> 158963 | I11: 30546 | J11: 62561 | K11: 33534 | L11: 31684 | M11: 7134 | N11: =SUM(I11:M11) -> 165459
A12: 2023-02-24 | B12: 27974 | C12: 60496 | D12: 31590 | E12: 31506 | F12: 7684 | G12: =SUM(B12:F12) -> 159250 | I12: 30593 | J12: 62611 | K12: 33570 | L12: 31780 | M12: 7131 | N12: =SUM(I12:M12) -> 165685
A13: 2023-03-03 | B13: 28029 | C13: 60535 | D13: 31629 | E13: 31526 | F13: 7655 | G13: =SUM(B13:F13) -> 159374 | I13: 30641 | J13: 62662 | K13: 33606 | L13: 31784 | M13: 7127 | N13: =SUM(I13:M13) -> 165820
A14: 2023-03-10 | B14: 28085 | C14: 60611 | D14: 31668 | E14: 31530 | F14: 8333 | G14: =SUM(B14:F14) -> 160227 | I14: 30688 | J14: 62868 | K14: 33642 | L14: 31796 | M14: 7853 | N14: =SUM(I14:M14) -> 166847
A15: 2023-03-17 | B15: 28145 | C15: 60417 | D15: 31670 | E15: 31465 | F15: 8125 | G15: =SUM(B15:F15) -> 159822 | I15: 30753 | J15: 62604 | K15: 33553 | L15: 31830 | M15: 7628 | N15: =SUM(I15:M15) -> 166368
A16: 2023-03-24 | B16: 28201 | C16: 60459 | D16: 31724 | E16: 31449 | F16: 8143 | G16: =SUM(B16:F16) -> 159976 | I16: 30801 | J16: 62648 | K16: 33582 | L16: 31781 | M16: 7646 | N16: =SUM(I16:M16) -> 166458
... A184: 2026-06-12 | B184: 177406 | C184: 212156 | D184: 211122 | E184: 146769 | F184: 80465 | G184: =SUM(B184:F184) -> 827918 | I184: 200884 | J184: 231403 | K184: 248385 | L184: 168878 | M184: 96629 | N184: =SUM(I184:M184) -> 946179

Sheet PPE MSFT
A1: Microsoft — Property & Equipment, gross by category (US$ mn)
A2: Source: SEC XBRL companyfacts, us-gaap tagged 10-K values, FY ends 30-Jun (https://data.sec.gov/api/xbrl/companyfacts/CIK0000789019.json). 'Computer equipment and software' is not separately tagged — derived as gross minus tagged components (formula). MSFT does not disclose CIP separately; construction in progress sits within categories.
A4: Category | B4: FY15 | C4: FY16 | D4: FY17 | E4: FY18 | F4: FY19 | G4: FY20 | H4: FY21 | I4: FY22 | J4: FY23 | K4: FY24 | L4: FY25
A5: Land | B5: 769 | C5: 824 | D5: 1107 | E5: 1254 | F5: 1540 | G5: 1823 | H5: 3660 | I5: 4734 | J5: 5683 | K5: 8163 | L5: 9338
A6: Buildings and improvements | B6: 10800 | C6: 12393 | D6: 16284 | E6: 20604 | F6: 26288 | G6: 33995 | H6: 43928 | I6: 55014 | J6: 68465 | K6: 93943 | L6: 137921
A7: Leasehold improvements | B7: 3577 | C7: 3659 | D7: 5064 | E7: 4735 | F7: 5316 | G7: 5487 | H7: 6884 | I7: 7819 | J7: 8537 | K7: 9594 | L7: 12117
A8: Furniture and equipment | B8: 3579 | C8: 3889 | D8: 4044 | E8: 4457 | F8: 4840 | G8: 4782 | H8: 5344 | I8: 5860 | J8: 6246 | K8: 6532 | L8: 6407
A9: Computer equipment and software (derived) | B9: =B10-B5-B6-B7-B8 -> 13612 | C9: =C10-C5-C6-C7-C8 -> 17391 | D9: =D10-D5-D6-D7-D8 -> 21414 | E9: =E10-E5-E6-E7-E8 -> 27633 | F9: =F10-F5-F6-F7-F8 -> 33823 | G9: =G10-G5-G6-G7-G8 -> 41261 | H9: =H10-H5-H6-H7-H8 -> 51250 | I9: =I10-I5-I6-I7-I8 -> 60631 | ... L9: =L10-L5-L6-L7-L8 -> 132836
A10: Total gross PP&E (reported) | B10: 32337 | C10: 38156 | D10: 47913 | E10: 58683 | F10: 71807 | G10: 87348 | H10: 111066 | I10: 134058 | J10: 163892 | K10: 212012 | L10: 298619
A11: Accumulated depreciation | B11: -17606 | C11: -19800 | D11: -24179 | E11: -29223 | F11: -35330 | G11: -43197 | H11: -51351 | I11: -59660 | J11: -68251 | K11: -76421 | L11: -93653
A12: Net PP&E (calc) | B12: =B10+B11 -> 14731 | C12: =C10+C11 -> 18356 | D12: =D10+D11 -> 23734 | E12: =E10+E11 -> 29460 | F12: =F10+F11 -> 36477 | G12: =G10+G11 -> 44151 | H12: =H10+H11 -> 59715 | I12: =I10+I11 -> 74398 | ... L12: =L10+L11 -> 204966
A13: Net PP&E (reported) | B13: 14731 | C13: 18356 | D13: 23734 | E13: 29460 | F13: 36477 | G13: 44151 | H13: 59715 | I13: 74398 | J13: 95641 | K13: 135591 | L13: 204966
A15: EQUIPMENT vs LONG-TERM ASSETS (gross)
A16: Equipment (computer equip & software) | B16: =B9 -> 13612 | C16: =C9 -> 17391 | D16: =D9 -> 21414 | E16: =E9 -> 27633 | F16: =F9 -> 33823 | G16: =G9 -> 41261 | H16: =H9 -> 51250 | I16: =I9 -> 60631 | ... L16: =L9 -> 132836
A17: Long-term assets (land, buildings, leasehold) | B17: =B5+B6+B7 -> 15146 | C17: =C5+C6+C7 -> 16876 | D17: =D5+D6+D7 -> 22455 | E17: =E5+E6+E7 -> 26593 | F17: =F5+F6+F7 -> 33144 | G17: =G5+G6+G7 -> 41305 | H17: =H5+H6+H7 -> 54472 | I17: =I5+I6+I7 -> 67567 | ... L17: =L5+L6+L7 -> 159376
A18: Other (furniture & equipment) | B18: =B8 -> 3579 | C18: =C8 -> 3889 | D18: =D8 -> 4044 | E18: =E8 -> 4457 | F18: =F8 -> 4840 | G18: =G8 -> 4782 | H18: =H8 -> 5344 | I18: =I8 -> 5860 | ... L18: =L8 -> 6407
A19: Equipment (computer equip & software) % of gross | B19: =IF(OR(B10="",B10=0),"-",B16/B10) -> 0.42094196 | C19: =IF(OR(C10="",C10=0),"-",C16/C10) -> 0.45578677 | D19: =IF(OR(D10="",D10=0),"-",D16/D10) -> 0.44693507 | E19: =IF(OR(E10="",E10=0),"-",E16/E10) -> 0.47088595 | F19: =IF(OR(F10="",F10=0),"-",F16/F10) -> 0.4710265 | G19: =IF(OR(G10="",G10=0),"-",G16/G10) -> 0.47237487 | H19: =IF(OR(H10="",H10=0),"-",H16/H10) -> 0.46143734 | I19: =IF(OR(I10="",I10=0),"-",I16/I10) -> 0.45227439 | ... L19: =IF(OR(L10="",L10=0),"-",L16/L10) -> 0.44483439
A20: Long-term assets (land, buildings, leasehold) % of gross | B20: =IF(OR(B10="",B10=0),"-",B17/B10) -> 0.46837987 | C20: =IF(OR(C10="",C10=0),"-",C17/C10) -> 0.44228955 | D20: =IF(OR(D10="",D10=0),"-",D17/D10) -> 0.46866195 | E20: =IF(OR(E10="",E10=0),"-",E17/E10) -> 0.45316361 | F20: =IF(OR(F10="",F10=0),"-",F17/F10) -> 0.4615706 | G20: =IF(OR(G10="",G10=0),"-",G17/G10) -> 0.4728786 | H20: =IF(OR(H10="",H10=0),"-",H17/H10) -> 0.49044712 | I20: =IF(OR(I10="",I10=0),"-",I17/I10) -> 0.50401319 | ... L20: =IF(OR(L10="",L10=0),"-",L17/L10) -> 0.53371018
A21: Other (furniture & equipment) % of gross | B21: =IF(OR(B10="",B10=0),"-",B18/B10) -> 0.11067817 | C21: =IF(OR(C10="",C10=0),"-",C18/C10) -> 0.10192368 | D21: =IF(OR(D10="",D10=0),"-",D18/D10) -> 0.08440298 | E21: =IF(OR(E10="",E10=0),"-",E18/E10) -> 0.075950446 | F21: =IF(OR(F10="",F10=0),"-",F18/F10) -> 0.067402899 | G21: =IF(OR(G10="",G10=0),"-",G18/G10) -> 0.054746531 | H21: =IF(OR(H10="",H10=0),"-",H18/H10) -> 0.048115535 | I21: =IF(OR(I10="",I10=0),"-",I18/I10) -> 0.043712423 | ... L21: =IF(OR(L10="",L10=0),"-",L18/L10) -> 0.021455433

Sheet PPE ORCL
A1: Oracle — Property & Equipment, gross by category (US$ mn)
A2: Source: SEC XBRL companyfacts, us-gaap tagged 10-K values, FY ends 31-May (https://data.sec.gov/api/xbrl/companyfacts/CIK0001341439.json). FY26 10-K not yet filed as of build date. 'Computer, communication equip.' = us-gaap:MachineryAndEquipmentGross (untagged before FY2018).
A4: Category | B4: FY15 | C4: FY16 | D4: FY17 | E4: FY18 | F4: FY19 | G4: FY20 | H4: FY21 | I4: FY22 | J4: FY23 | K4: FY24 | L4: FY25
A5: Land | B5: 589 | C5: 744 | D5: 830 | E5: 868 | F5: 896 | G5: 885 | H5: 871 | I5: 1166 | J5: 1243 | K5: 1239 | L5: 1352
A6: Buildings and improvements | B6: 2721 | C6: 2754 | D6: 3466 | E6: 3893 | F6: 4253 | G6: 4394 | H6: 4734 | I6: 4729 | J6: 5880 | K6: 6493 | L6: 10881
A7: Computer, communication equip. | B7: 3345 | C7: 3927 | D7: 5112 | E7: 6156 | F7: 7214 | G7: 7757 | H7: 9508 | I7: 12844 | J7: 17258 | K7: 20989 | L7: 30345
A8: Construction in progress | B8: 93 | C8: 97 | D8: 235 | E8: 229 | F8: 158 | G8: 280 | H8: 233 | I8: 512 | J8: 3846 | K8: 5634 | L8: 16510
A9: Furniture and fixtures | B9: 547 | C9: 574 | D9: 651 | E9: 662 | F9: 554 | G9: 509 | H9: 454 | I9: 423 | J9: 447 | K9: 463 | L9: 466
A10: Total gross PP&E (reported) | B10: 7295 | C10: 8096 | D10: 10294 | E10: 11808 | F10: 13075 | G10: 13825 | H10: 15800 | I10: 19674 | J10: 28674 | K10: 34818 | L10: 59554
A11: Accumulated depreciation | B11: -3609 | C11: -4096 | D11: -4979 | E11: -5911 | F11: -6823 | G11: -7581 | H11: -8751 | I11: -9958 | J11: -11605 | K11: -13282 | L11: -16032
A12: Net PP&E (calc) | B12: =B10+B11 -> 3686 | C12: =C10+C11 -> 4000 | D12: =D10+D11 -> 5315 | E12: =E10+E11 -> 5897 | F12: =F10+F11 -> 6252 | G12: =G10+G11 -> 6244 | H12: =H10+H11 -> 7049 | I12: =I10+I11 -> 9716 | ... L12: =L10+L11 -> 43522
A13: Net PP&E (reported) | B13: 3686 | C13: 4000 | D13: 5315 | E13: 5897 | F13: 6252 | G13: 6244 | H13: 7049 | I13: 9716 | J13: 17069 | K13: 21536 | L13: 43522
A15: EQUIPMENT vs LONG-TERM ASSETS (gross)
A16: Equipment (computer & comms) | B16: =B7 -> 3345 | C16: =C7 -> 3927 | D16: =D7 -> 5112 | E16: =E7 -> 6156 | F16: =F7 -> 7214 | G16: =G7 -> 7757 | H16: =H7 -> 9508 | I16: =I7 -> 12844 | ... L16: =L7 -> 30345
A17: Long-term assets (land, buildings) | B17: =B5+B6 -> 3310 | C17: =C5+C6 -> 3498 | D17: =D5+D6 -> 4296 | E17: =E5+E6 -> 4761 | F17: =F5+F6 -> 5149 | G17: =G5+G6 -> 5279 | H17: =H5+H6 -> 5605 | I17: =I5+I6 -> 5895 | ... L17: =L5+L6 -> 12233
A18: Construction in progress | B18: =B8 -> 93 | C18: =C8 -> 97 | D18: =D8 -> 235 | E18: =E8 -> 229 | F18: =F8 -> 158 | G18: =G8 -> 280 | H18: =H8 -> 233 | I18: =I8 -> 512 | ... L18: =L8 -> 16510
A19: Other (furniture & fixtures) | B19: =B9 -> 547 | C19: =C9 -> 574 | D19: =D9 -> 651 | E19: =E9 -> 662 | F19: =F9 -> 554 | G19: =G9 -> 509 | H19: =H9 -> 454 | I19: =I9 -> 423 | ... L19: =L9 -> 466
A20: Equipment (computer & comms) % of gross | B20: =IF(OR(B10="",B10=0),"-",B16/B10) -> 0.45853324 | C20: =IF(OR(C10="",C10=0),"-",C16/C10) -> 0.48505435 | D20: =IF(OR(D10="",D10=0),"-",D16/D10) -> 0.49659996 | E20: =IF(OR(E10="",E10=0),"-",E16/E10) -> 0.52134146 | F20: =IF(OR(F10="",F10=0),"-",F16/F10) -> 0.55173996 | G20: =IF(OR(G10="",G10=0),"-",G16/G10) -> 0.56108499 | H20: =IF(OR(H10="",H10=0),"-",H16/H10) -> 0.60177215 | I20: =IF(OR(I10="",I10=0),"-",I16/I10) -> 0.65284131 | ... L20: =IF(OR(L10="",L10=0),"-",L16/L10) -> 0.50953756
A21: Long-term assets (land, buildings) % of gross | B21: =IF(OR(B10="",B10=0),"-",B17/B10) -> 0.45373544 | C21: =IF(OR(C10="",C10=0),"-",C17/C10) -> 0.43206522 | D21: =IF(OR(D10="",D10=0),"-",D17/D10) -> 0.41733048 | E21: =IF(OR(E10="",E10=0),"-",E17/E10) -> 0.40320122 | F21: =IF(OR(F10="",F10=0),"-",F17/F10) -> 0.39380497 | G21: =IF(OR(G10="",G10=0),"-",G17/G10) -> 0.38184448 | H21: =IF(OR(H10="",H10=0),"-",H17/H10) -> 0.35474684 | I21: =IF(OR(I10="",I10=0),"-",I17/I10) -> 0.29963403 | ... L21: =IF(OR(L10="",L10=0),"-",L17/L10) -> 0.20541022
A22: Construction in progress % of gross | B22: =IF(OR(B10="",B10=0),"-",B18/B10) -> 0.012748458 | C22: =IF(OR(C10="",C10=0),"-",C18/C10) -> 0.011981225 | D22: =IF(OR(D10="",D10=0),"-",D18/D10) -> 0.022828832 | E22: =IF(OR(E10="",E10=0),"-",E18/E10) -> 0.019393631 | F22: =IF(OR(F10="",F10=0),"-",F18/F10) -> 0.01208413 | G22: =IF(OR(G10="",G10=0),"-",G18/G10) -> 0.020253165 | H22: =IF(OR(H10="",H10=0),"-",H18/H10) -> 0.014746835 | I22: =IF(OR(I10="",I10=0),"-",I18/I10) -> 0.026024194 | ... L22: =IF(OR(L10="",L10=0),"-",L18/L10) -> 0.27722739
A23: Other (furniture & fixtures) % of gross | B23: =IF(OR(B10="",B10=0),"-",B19/B10) -> 0.074982865 | C23: =IF(OR(C10="",C10=0),"-",C19/C10) -> 0.070899209 | D23: =IF(OR(D10="",D10=0),"-",D19/D10) -> 0.063240723 | E23: =IF(OR(E10="",E10=0),"-",E19/E10) -> 0.056063686 | F23: =IF(OR(F10="",F10=0),"-",F19/F10) -> 0.042370937 | G23: =IF(OR(G10="",G10=0),"-",G19/G10) -> 0.03681736 | H23: =IF(OR(H10="",H10=0),"-",H19/H10) -> 0.028734177 | I23: =IF(OR(I10="",I10=0),"-",I19/I10) -> 0.021500457 | ... L23: =IF(OR(L10="",L10=0),"-",L19/L10) -> 0.0078248312

Sheet PPE AMZN
A1: Amazon — Property & Equipment, gross by category (US$ mn)
A2: Source: Amazon 10-K, Note — Property and Equipment (FY22 10-K filed 2023-02-03 through FY25 10-K filed 2026-02-06, SEC EDGAR CIK 1018724). FY25 10-K introduces the Servers & networking / Heavy equipment / Other equipment split (FY24 restated on that basis). Includes finance-lease assets per Amazon presentation.
A4: Category | B4: FY21 | C4: FY22 | D4: FY23 | E4: FY24 | F4: FY25
A5: Land and buildings | B5: 81104 | C5: 91650 | D5: 105293 | E5: 123039 | F5: 155121
A6: Equipment (total) | B6: 128683 | C6: 157458 | D6: 185039 | E6: 218893 | F6: 301413
A7: o/w Servers and networking | E7: 113156 | F7: 172492
A8: o/w Heavy equipment | E8: 52228 | F8: 65545
A9: o/w Other equipment | E9: 53509 | F9: 63376
A10: Other assets | B10: 4118 | C10: 4602 | D10: 5116 | E10: 5487 | F10: 5819
A11: Construction in progress | B11: 24895 | C11: 30020 | D11: 28840 | E11: 46636 | F11: 71745
A12: Total gross PP&E (reported) | B12: 238800 | C12: 283730 | D12: 324288 | E12: 394055 | F12: 534098
A13: Accumulated depreciation & amort. | B13: -78519 | C13: -97015 | D13: -120111 | E13: -141390 | F13: -177073
A14: Net PP&E (calc) | B14: =B12+B13 -> 160281 | C14: =C12+C13 -> 186715 | D14: =D12+D13 -> 204177 | E14: =E12+E13 -> 252665 | F14: =F12+F13 -> 357025
A15: Net PP&E (reported) | B15: 160281 | C15: 186715 | D15: 204177 | E15: 252665 | F15: 357025
A17: EQUIPMENT vs LONG-TERM ASSETS (gross)
A18: Equipment (incl. servers & networking) | B18: =B6 -> 128683 | C18: =C6 -> 157458 | D18: =D6 -> 185039 | E18: =E6 -> 218893 | F18: =F6 -> 301413
A19: Long-term assets (land and buildings) | B19: =B5 -> 81104 | C19: =C5 -> 91650 | D19: =D5 -> 105293 | E19: =E5 -> 123039 | F19: =F5 -> 155121
A20: Construction in progress | B20: =B11 -> 24895 | C20: =C11 -> 30020 | D20: =D11 -> 28840 | E20: =E11 -> 46636 | F20: =F11 -> 71745
A21: Other assets | B21: =B10 -> 4118 | C21: =C10 -> 4602 | D21: =D10 -> 5116 | E21: =E10 -> 5487 | F21: =F10 -> 5819
A22: Equipment (incl. servers & networking) % of gross | B22: =IF(OR(B12="",B12=0),"-",B18/B12) -> 0.53887353 | C22: =IF(OR(C12="",C12=0),"-",C18/C12) -> 0.55495718 | D22: =IF(OR(D12="",D12=0),"-",D18/D12) -> 0.57060082 | E22: =IF(OR(E12="",E12=0),"-",E18/E12) -> 0.55548845 | F22: =IF(OR(F12="",F12=0),"-",F18/F12) -> 0.56434025
A23: Long-term assets (land and buildings) % of gross | B23: =IF(OR(B12="",B12=0),"-",B19/B12) -> 0.33963149 | C23: =IF(OR(C12="",C12=0),"-",C19/C12) -> 0.32301836 | D23: =IF(OR(D12="",D12=0),"-",D19/D12) -> 0.32468978 | E23: =IF(OR(E12="",E12=0),"-",E19/E12) -> 0.31223814 | F23: =IF(OR(F12="",F12=0),"-",F19/F12) -> 0.29043546
A24: Construction in progress % of gross | B24: =IF(OR(B12="",B12=0),"-",B20/B12) -> 0.10425042 | C24: =IF(OR(C12="",C12=0),"-",C20/C12) -> 0.10580481 | D24: =IF(OR(D12="",D12=0),"-",D20/D12) -> 0.088933294 | E24: =IF(OR(E12="",E12=0),"-",E20/E12) -> 0.11834896 | F24: =IF(OR(F12="",F12=0),"-",F20/F12) -> 0.13432928
A25: Other assets % of gross | B25: =IF(OR(B12="",B12=0),"-",B21/B12) -> 0.017244556 | C25: =IF(OR(C12="",C12=0),"-",C21/C12) -> 0.016219645 | D25: =IF(OR(D12="",D12=0),"-",D21/D12) -> 0.0157761 | E25: =IF(OR(E12="",E12=0),"-",E21/E12) -> 0.013924452 | F25: =IF(OR(F12="",F12=0),"-",F21/F12) -> 0.010895004
A27: FY25 servers & networking equipment $172.5bn gross = 32% of gross PP&E. Equipment (total) FY24/FY25 = sum of the three sub-rows (latest-filing presentation).

Sheet PPE GOOGL
A1: Alphabet — Property & Equipment, gross by category (US$ mn)
A2: Source: Alphabet 10-K, Note 7 — Property and Equipment (FY24 10-K filed 2025-02-05, FY25 10-K filed 2026-02-05, SEC EDGAR CIK 1652044). FY24 10-K recast the note to Technical infrastructure (servers, network equipment, data-center land & buildings) / Office space / Corporate & other, on an IN-SERVICE basis with 'assets not yet in service' shown separately. FY2024 restated between filings — latest filing used. NOTE: GOOGL's 'Technical infrastructure' INCLUDES data-center real estate, so Equipment here is broader than servers alone.
A4: Category | B4: FY23 | C4: FY24 | D4: FY25
A5: Technical infrastructure | B5: 112504 | C5: 141852 | D5: 203679
A6: Office space | B6: 40435 | C6: 45403 | D6: 48348
A7: Corporate and other assets | B7: 13728 | C7: 12574 | D7: 14463
A8: Total gross PP&E (reported, in service) | B8: 166667 | C8: 199829 | D8: 266490
A9: Assets not yet in service (CIP-like) | B9: 35136 | C9: 50597 | D9: 78592
A10: Accumulated depreciation | B10: -67458 | C10: -79390 | D10: -98485
A11: Net PP&E (calc) | B11: =B8+B9+B10 -> 134345 | C11: =C8+C9+C10 -> 171036 | D11: =D8+D9+D10 -> 246597
A12: Net PP&E (reported) | B12: 134345 | C12: 171036 | D12: 246597
A14: EQUIPMENT vs LONG-TERM ASSETS (gross)
A15: Equipment (technical infrastructure) | B15: =B5 -> 112504 | C15: =C5 -> 141852 | D15: =D5 -> 203679
A16: Long-term assets (office space) | B16: =B6 -> 40435 | C16: =C6 -> 45403 | D16: =D6 -> 48348
A17: Assets not yet in service (CIP-like) | B17: =B9 -> 35136 | C17: =C9 -> 50597 | D17: =D9 -> 78592
A18: Other (corporate & other) | B18: =B7 -> 13728 | C18: =C7 -> 12574 | D18: =D7 -> 14463
A19: Equipment (technical infrastructure) % of gross | B19: =IF(OR(B8="",B8=0),"-",B15/B8) -> 0.67502265 | C19: =IF(OR(C8="",C8=0),"-",C15/C8) -> 0.70986694 | D19: =IF(OR(D8="",D8=0),"-",D15/D8) -> 0.7643026
A20: Long-term assets (office space) % of gross | B20: =IF(OR(B8="",B8=0),"-",B16/B8) -> 0.24260951 | C20: =IF(OR(C8="",C8=0),"-",C16/C8) -> 0.22720926 | D20: =IF(OR(D8="",D8=0),"-",D16/D8) -> 0.18142519
A21: Assets not yet in service (CIP-like) % of gross | B21: =IF(OR(B8="",B8=0),"-",B17/B8) -> 0.21081558 | C21: =IF(OR(C8="",C8=0),"-",C17/C8) -> 0.25320149 | D21: =IF(OR(D8="",D8=0),"-",D17/D8) -> 0.29491538
A22: Other (corporate & other) % of gross | B22: =IF(OR(B8="",B8=0),"-",B18/B8) -> 0.082367835 | C22: =IF(OR(C8="",C8=0),"-",C18/C8) -> 0.0629238 | D22: =IF(OR(D8="",D8=0),"-",D18/D8) -> 0.054272205
A24: Legacy presentation (FY23 10-K, FY ends Dec): FY22/FY23 — Land and buildings 66,897/74,083 · Information technology assets 66,267/80,594 · Construction in progress 27,657/35,229 · Leasehold improvements 10,575/11,425 · Furniture and fixtures 314/472 · Gross 171,710/201,803 · Accum dep (59,042)/(67,458) · Net 112,668/134,345.

Sheet PPE META
A1: Meta — Property & Equipment, gross by category (US$ mn)
A2: Source: Meta 10-K, PP&E note (FY24 10-K filed 2025-01-30, FY25 10-K filed 2026-01-29, SEC EDGAR CIK 1326801). Note: Meta lists the CURRENT year first in its table (handled). Finance lease ROU assets kept in Other (mixed nature).
A4: Category | B4: FY23 | C4: FY24 | D4: FY25
A5: Land | B5: 2080 | C5: 2561 | D5: 3687
A6: Buildings | B6: 37961 | C6: 47076 | D6: 55568
A7: Leasehold improvements | B7: 6972 | C7: 7293 | D7: 8346
A8: Servers and network assets | B8: 46838 | C8: 68397 | D8: 98040
A9: Equipment and other | B9: 7416 | C9: 7150 | D9: 9377
A10: Finance lease right-of-use assets | B10: 4185 | C10: 5384 | D10: 8187
A11: Construction in progress | B11: 24269 | C11: 26802 | D11: 50521
A12: Total gross PP&E (reported) | B12: 129721 | C12: 164663 | D12: 233726
A13: Accumulated depreciation | B13: -33134 | C13: -43317 | D13: -57326
A14: Net PP&E (calc) | B14: =B12+B13 -> 96587 | C14: =C12+C13 -> 121346 | D14: =D12+D13 -> 176400
A15: Net PP&E (reported) | B15: 96587 | C15: 121346 | D15: 176400
A17: EQUIPMENT vs LONG-TERM ASSETS (gross)
A18: Equipment (servers & network assets) | B18: =B8 -> 46838 | C18: =C8 -> 68397 | D18: =D8 -> 98040
A19: Long-term assets (land, buildings, leasehold) | B19: =B5+B6+B7 -> 47013 | C19: =C5+C6+C7 -> 56930 | D19: =D5+D6+D7 -> 67601
A20: Construction in progress | B20: =B11 -> 24269 | C20: =C11 -> 26802 | D20: =D11 -> 50521
A21: Other (equipment & other, finance leases) | B21: =B9+B10 -> 11601 | C21: =C9+C10 -> 12534 | D21: =D9+D10 -> 17564
A22: Equipment (servers & network assets) % of gross | B22: =IF(OR(B12="",B12=0),"-",B18/B12) -> 0.36106721 | C22: =IF(OR(C12="",C12=0),"-",C18/C12) -> 0.41537565 | D22: =IF(OR(D12="",D12=0),"-",D18/D12) -> 0.41946553
A23: Long-term assets (land, buildings, leasehold) % of gross | B23: =IF(OR(B12="",B12=0),"-",B19/B12) -> 0.36241626 | C23: =IF(OR(C12="",C12=0),"-",C19/C12) -> 0.34573644 | D23: =IF(OR(D12="",D12=0),"-",D19/D12) -> 0.28923184
A24: Construction in progress % of gross | B24: =IF(OR(B12="",B12=0),"-",B20/B12) -> 0.18708613 | C24: =IF(OR(C12="",C12=0),"-",C20/C12) -> 0.16276881 | D24: =IF(OR(D12="",D12=0),"-",D20/D12) -> 0.21615481
A25: Other (equipment & other, finance leases) % of gross | B25: =IF(OR(B12="",B12=0),"-",B21/B12) -> 0.089430393 | C25: =IF(OR(C12="",C12=0),"-",C21/C12) -> 0.076119104 | D25: =IF(OR(D12="",D12=0),"-",D21/D12) -> 0.075147823

Sheet PPE Summary
A1: PP&E Summary — Equipment vs long-term assets, latest fiscal year (gross, US$ mn)
A2: Green = links to the per-company PPE tabs. Buckets follow each company's own disclosure (see PPE tabs for caveats — e.g. GOOGL technical infrastructure includes DC real estate; MSFT has no separate CIP line; AMZN equipment includes fulfillment/transport gear).
A4: Company (latest FY) | B4: Equipment | C4: LT assets (real estate) | D4: CIP / not in service | E4: Other | F4: Total gross | G4: Equipment % gross | H4: LT % gross | I4: CIP % gross
A5: Microsoft (FY25) | B5: ='PPE MSFT'!L16 -> 132836 | C5: ='PPE MSFT'!L17 -> 159376 | E5: ='PPE MSFT'!L18 -> 6407 | F5: ='PPE MSFT'!L10 -> 298619 | G5: =B5/F5 -> 0.44483439 | H5: =C5/F5 -> 0.53371018 | I5: =IF(D5="","-",D5/F5) -> -
A6: Amazon (FY25) | B6: ='PPE AMZN'!F18 -> 301413 | C6: ='PPE AMZN'!F19 -> 155121 | D6: ='PPE AMZN'!F20 -> 71745 | E6: ='PPE AMZN'!F21 -> 5819 | F6: ='PPE AMZN'!F12 -> 534098 | G6: =B6/F6 -> 0.56434025 | H6: =C6/F6 -> 0.29043546 | I6: =IF(D6="","-",D6/F6) -> 0.13432928
A7: Alphabet (FY25) | B7: ='PPE GOOGL'!D15 -> 203679 | C7: ='PPE GOOGL'!D16 -> 48348 | D7: ='PPE GOOGL'!D17 -> 78592 | E7: ='PPE GOOGL'!D18 -> 14463 | F7: ='PPE GOOGL'!D8 -> 266490 | G7: =B7/F7 -> 0.7643026 | H7: =C7/F7 -> 0.18142519 | I7: =IF(D7="","-",D7/F7) -> 0.29491538
A8: Meta (FY25) | B8: ='PPE META'!D18 -> 98040 | C8: ='PPE META'!D19 -> 67601 | D8: ='PPE META'!D20 -> 50521 | E8: ='PPE META'!D21 -> 17564 | F8: ='PPE META'!D12 -> 233726 | G8: =B8/F8 -> 0.41946553 | H8: =C8/F8 -> 0.28923184 | I8: =IF(D8="","-",D8/F8) -> 0.21615481
A9: Oracle (FY25) | B9: ='PPE ORCL'!L16 -> 30345 | C9: ='PPE ORCL'!L17 -> 12233 | D9: ='PPE ORCL'!L18 -> 16510 | E9: ='PPE ORCL'!L19 -> 466 | F9: ='PPE ORCL'!L10 -> 59554 | G9: =B9/F9 -> 0.50953756 | H9: =C9/F9 -> 0.20541022 | I9: =IF(D9="","-",D9/F9) -> 0.27722739
A10: Big-5 total | B10: =SUM(B5:B9) -> 766313 | C10: =SUM(C5:C9) -> 442679 | D10: =SUM(D5:D9) -> 217368 | E10: =SUM(E5:E9) -> 44719 | F10: =SUM(F5:F9) -> 1392487 | G10: =B10/F10 -> 0.55031968 | H10: =C10/F10 -> 0.3179053 | I10: =D10/F10 -> 0.15610056
A12: Fiscal years differ: MSFT FY25 ends Jun-25, ORCL FY25 ends May-25, others Dec-25. MSFT Equipment is the derived computer equipment & software line.
